{
    "$schema": "http://schema.management.azure.com/schemas/2015-01-01/deploymentTemplate.json",
    "contentVersion": "1.0.0.0",
    "parameters": {
        "deploymentPrefix": {
            "type": "string"
        },
        "location": {
            "type": "string"
        },
        "resourceGroupPrefix": {
            "type": "string"
        },
        "environmentReference": {
            "type": "object"
        },
        "networkReference": {
            "type": "array"
        },
        "vmReference": {
            "type": "array"
        }
    },
    "variables": {
        "natStartPort": 50000,
        "natEndPort": 50119,
        "natBackendPortUbuntu": 22,
        "natBackendPortWindows": 3389,
        "Ubuntu": {
            "publisher": "Canonical",
            "offer": "UbuntuServer",
            "sku": "16.04.0-LTS",
            "version": "latest"
        },
        "Windows": {
            "publisher": "MicrosoftWindowsServer",
            "offer": "WindowsServer",
            "sku": "2016-Datacenter",
            "version": "latest"
        },
        "computeApiVersion": "2017-03-30",
        "networkApiVersion": "2017-04-01"
    },
    "resources": [
        {
            "condition": "[equals(parameters('vmReference')[copyIndex()].balancer, 'ilb')]",
            "type": "Microsoft.Network/loadBalancers",
            "name": "[concat(parameters('deploymentPrefix'), '-', parameters('vmReference')[copyIndex()].name, '-ilb')]",
            "location": "[parameters('location')]",
            "apiVersion": "[variables('networkApiVersion')]",
            "copy": {
                "name": "lbcopy",
                "count": "[length(parameters('vmReference'))]"
            },
            "properties": {
                "frontendIPConfigurations": [
                    {
                        "name": "LoadBalancerFrontEnd",
                        "properties": {
                            "subnet": {
                                "id": "[concat(resourceId(concat(parameters('resourceGroupPrefix'), '-', parameters('deploymentPrefix'), '-networking'), 'Microsoft.Network/virtualNetworks', concat(parameters('deploymentPrefix'), '-', parameters('vmReference')[copyIndex()].vnet)), '/subnets/', parameters('vmReference')[copyIndex()].subnet)]"
                            }
                        }
                    }
                ],
                "backendAddressPools": [
                    {
                        "name": "[concat(parameters('vmReference')[copyIndex()].name, '-bePoolName')]"
                    }
                ],
                "inboundNatPools": [
                    {
                        "name": "[concat(parameters('vmReference')[copyIndex()].name, '-natPoolName')]",
                        "properties": {
                            "frontendIPConfiguration": {
                                "id": "[concat(resourceId('Microsoft.Network/loadBalancers', concat(parameters('deploymentPrefix'), '-', parameters('vmReference')[copyIndex()].name, '-ilb')), '/frontendIPConfigurations/loadBalancerFrontEnd')]"
                            },
                            "protocol": "tcp",
                            "frontendPortRangeStart": "[variables('natStartPort')]",
                            "frontendPortRangeEnd": "[variables('natEndPort')]",
                            "backendPort": "[parameters('vmReference')[copyIndex()].port]"
                        }
                    }
                ]
            }
        },
        {
            "type": "Microsoft.Compute/virtualMachineScaleSets",
            "name": "[concat(parameters('deploymentPrefix'), '-', parameters('vmReference')[copyIndex()].name, '-vmss')]",
            "location": "[parameters('location')]",
            "apiVersion": "[variables('computeApiVersion')]",
            "copy": {
                "name": "vmsscopy",
                "count": "[length(parameters('vmReference'))]"
            },
            "sku": {
                "name": "[parameters('vmReference')[copyIndex()].size]",
                "tier": "Standard",
                "capacity": "[parameters('vmReference')[copyIndex()].count]"
            },
            "properties": {
                "overprovision": "true",
                "upgradePolicy": {
                    "mode": "Manual"
                },
                "virtualMachineProfile": {
                    "storageProfile": {
                        "osDisk": {
                            "createOption": "FromImage"
                        },
                        "imageReference": "[variables(parameters('vmReference')[copyIndex()].os)]"
                    },
                    "osProfile": {
                        "computerNamePrefix": "[parameters('vmReference')[copyIndex()].name]",
                        "adminUsername": "[parameters('vmReference')[copyIndex()].name]",
                        "adminPassword": "[parameters('vmReference')[copyIndex()].password]"
                    },
                    "networkProfile": {
                        "networkInterfaceConfigurations": [
                            {
                                "name": "vmssnicname",
                                "properties": {
                                    "primary": true,
                                    "ipConfigurations": [
                                        {
                                            "name": "[concat(parameters('vmReference')[copyIndex()].name, '-ipconfiguration')]",
                                            "properties": {
                                                "subnet": {
                                                    "id": "[concat(resourceId(concat(parameters('resourceGroupPrefix'), '-', parameters('deploymentPrefix'), '-networking'), 'Microsoft.Network/virtualNetworks', concat(parameters('deploymentPrefix'), '-', parameters('vmReference')[copyIndex()].vnet)), '/subnets/', parameters('vmReference')[copyIndex()].subnet)]"
                                                },
                                                "loadBalancerBackendAddressPools": [
                                                    {
                                                        "id": "[concat(resourceGroup().id, '/providers/Microsoft.Network/loadBalancers/', concat(parameters('deploymentPrefix'), '-', parameters('vmReference')[copyIndex()].name, '-ilb'), concat('/backendAddressPools/', parameters('vmReference')[copyIndex()].name, '-bePoolName'))]"
                                                    }
                                                ],
                                                "loadBalancerInboundNatPools": [
                                                    {
                                                        "id": "[concat(resourceGroup().id, '/providers/Microsoft.Network/loadBalancers/', concat(parameters('deploymentPrefix'), '-', parameters('vmReference')[copyIndex()].name, '-ilb'), concat('/inboundNatPools/', parameters('vmReference')[copyIndex()].name, '-natPoolName'))]"
                                                    }
                                                ]
                                            }
                                        }
                                    ]
                                }
                            }
                        ]
                    }
                }
            }
        }
    ]
}